{
  "url": "https://www.inmediahk.net/node/%E6%94%BF%E7%B6%93/%E6%B6%89youtube%E6%8A%AB%E9%9C%B2%E5%9C%8B%E5%AE%89%E6%9C%83%E9%9D%A2%E5%85%A7%E5%AE%B9-%E7%8E%8B%E5%B2%B8%E7%84%B6%E8%A2%AB%E6%8E%A7%E5%A6%A8%E5%AE%B3%E8%AA%BF%E6%9F%A5%E5%8F%8A%E7%85%BD%E5%8B%95-%E7%94%B3%E4%BF%9D%E9%87%8B%E8%A2%AB%E6%8B%92",
  "title": "涉YouTube披露國安會面內容 王岸然被控妨害調查及煽動 申保釋被拒",
  "source": "inmedia",
  "source_file": "content\\news\\inmedia\\README.md",
  "scraped_at": "2025-12-12T21:48:22.375751",
  "archive_path": "content\\news\\inmedia\\archive\\涉youtube披露國安會面內容-王岸然被控妨害調查及煽動-申保釋被拒"
}